Workbook

Sheet PREMISSAS
A1: PREMISSAS — preencha SÓ as células AMARELAS
A2: A companhia e a antecedência moram aqui, e SÓ aqui. Toda a aba COMITIVA lê estas células com referência absoluta ($B$5). Trocou a cia? Troca em B5 e a comitiva inteira recalcula o custo. AMARELO = você escolhe | CINZA = fórmula, não digite por cima.
A4: Premissa | B4: Valor | C4: Unidade | D4: Origem do dado | E4: Por que isso importa
A5: Companhia aérea | B5: GOL | C5: lista | D5: ESCOLHA (lista suspensa) | E5: LATAM não publica preço de despacho — é dinâmico. Escolha LATAM e veja a planilha avisar em vez de inventar número.
A6: Antecedência da compra do despacho | B6: 48h ou mais | C6: lista | D6: ESCOLHA (lista suspensa) | E6: GOL: 1ª peça R$ 130 antecipado × R$ 180 no balcão do aeroporto. Comprar bagagem em cima da hora é dinheiro jogado fora.
A7: Nº de trechos (ida e volta = 2) | B7: 2 | C7: trechos | D7: PREMISSA DO ALUNO | E7: Bagagem se paga POR TRECHO. Orçar só a ida é o erro mais comum de comitiva.
A9: CALCULADO (não digite por cima)
A10: Nº de pessoas na comitiva | B10: =COUNTA(COMITIVA!$A$6:$A$45) | C10: pessoas | D10: FÓRMULA — conta os nomes da aba COMITIVA. Uma célula, uma verdade: não se digita gente aqui, se digita gente lá.
A11: Chave de consulta da tabela oficial | B11: =$B$5&"|"&$B$6 | C11: texto | D11: FÓRMULA — é a chave que o ÍNDICE+CORRESP usa em TABELAS_OFICIAIS
A12: Preço da 1ª peça despachada (resolvido) | B12: =IFERROR(INDEX(TABELAS_OFICIAIS!$D$6:$F$14,MATCH($B$11,TABELAS_OFICIAIS!$A$6:$A$14,0),1),"chave invalida") | C12: R$/peça/trecho | D12: TABELAS_OFICIAIS — dado oficial, snapshot 15/07/2026
A13: Preço da 2ª peça despachada (resolvido) | B13: =IFERROR(INDEX(TABELAS_OFICIAIS!$D$6:$F$14,MATCH($B$11,TABELAS_OFICIAIS!$A$6:$A$14,0),2),"chave invalida") | C13: R$/peça/trecho | D13: TABELAS_OFICIAIS — dado oficial, snapshot 15/07/2026
A14: Preço da 3ª a 5ª peça (resolvido) | B14: =IFERROR(INDEX(TABELAS_OFICIAIS!$D$6:$F$14,MATCH($B$11,TABELAS_OFICIAIS!$A$6:$A$14,0),3),"chave invalida") | C14: R$/peça/trecho | D14: TABELAS_OFICIAIS — dado oficial, snapshot 15/07/2026
A15: Preço do excesso 32–45 kg (resolvido) | B15: =IFERROR(INDEX(TABELAS_OFICIAIS!$B$21:$B$23,MATCH($B$5,TABELAS_OFICIAIS!$A$21:$A$23,0)),"chave invalida") | C15: R$/volume/trecho | D15: TABELAS_OFICIAIS — só a GOL publica (R$ 350)
A16: Preço da bagagem especial/diferenciada (resolvido) | B16: =IFERROR(INDEX(TABELAS_OFICIAIS!$B$27:$B$29,MATCH($B$5,TABELAS_OFICIAIS!$A$27:$A$29,0)),"chave invalida") | C16: R$/volume/trecho | D16: TABELAS_OFICIAIS — GOL R$ 195 (até 292 cm) | Azul R$ 250 (acima de 158 cm) | LATAM não publicado
A18: LIMITES QUE A ABA COMITIVA VIGIA (dado oficial — snapshot 15/07/2026)
A19: Peso da franquia por volume despachado | B19: 23 | C19: kg | D19: GOL / Azul / LATAM — 23 kg por volume
A20: Peso acima do qual a cia RECUSA o volume | B20: 45 | C20: kg | D20: GOL 45 kg BR / Azul 45 kg BR / LATAM não transporta acima de 45 kg. Acima disso: contrato de CARGA (Res. ANAC 400/2016, art. 15)
A21: Peso a partir do qual há excesso cobrável | B21: 32 | C21: kg | D21: Faixa publicada: 32→45 kg. A faixa 23→32 kg da GOL NÃO entra: duas páginas oficiais divergem (R$ 170 × R$ 275)
A22: Franquia mínima de bagagem de mão | B22: 10 | C22: kg | D22: Res. ANAC 400/2016, art. 14 — mínimo 10 kg. A norma NÃO fixa dimensão: 55×35×25 cm é contrato da cia, não 'padrão ANAC'
A23: Máximo de peças despachadas por passageiro/trecho | B23: 5 | C23: peças | D23: Azul — máx. 5 peças de 23 kg por passageiro/trecho

Sheet COMITIVA
A1: COMITIVA — quem leva o quê, quanto pesa, quanto custa
A2: Preencha as colunas AMARELAS (A a I). Da J em diante é tudo fórmula — não digite por cima. Vermelho claro = volume acima de 23 kg (você vai pagar excesso). Vermelho forte = acima de 45 kg: a companhia RECUSA, isso deixa de ser bagagem e vira contrato de carga (Res. ANAC 400/2016, art. 15). O custo sai por ÍNDICE+CORRESP na aba TABELAS_OFICIAIS, com a cia e a antecedência que estão em PREMISSAS.
A3: Bagagem de mão: franquia mínima de 10 kg (Res. ANAC 400/2016, art. 14). Dimensão NÃO é da norma — é do contrato da cia (GOL/LATAM 55×35×25 até 12 kg; Azul 55×35×25 / 115 cm até 10 kg). Case rígido (bumbo, contrabaixo, tuba, violoncelo) = bagagem ESPECIAL/DIFERENCIADA: use a coluna própria. Amplificador e caixa acústica na Azul são ARTIGO PERIGOSO: só até 95 cm somados e 1 por passageiro — acima vai de Azul Cargo.
A5: Nome | B5: Função | C5: Mala de mão (kg) | D5: Volumes despachados | E5: Peso vol. 1 (kg) | F5: Peso vol. 2 (kg) | G5: Peso vol. 3 (kg) | H5: Peso vol. 4 (kg) | I5: Peso vol. 5 (kg) | J5: Volumes especiais (case rígido) | K5: Peso total despachado (kg) | L5: Volume mais pesado (kg) | M5: Alerta mala de mão | N5: Alerta excesso (>23 kg) | O5: Alerta recusa (>45 kg) | P5: Custo do despacho (R$)
A6: Ana Ribeiro | B6: Produtora | C6: 9 | D6: 1 | E6: 20 | J6: 0 | K6: =IF($A6="","",SUM($E6:$I6)) | L6: =IF($A6="","",IF(COUNT($E6:$I6)=0,0,MAX($E6:$I6))) | M6: =IF($A6="","",IF($C6>PREMISSAS!$B$22,"acima de "&PREMISSAS!$B$22&" kg — confira o contrato da cia","ok")) | N6: =IF($A6="","",IF($L6>PREMISSAS!$B$19,"EXCESSO","ok")) | O6: =IF($A6="","",IF($L6>PREMISSAS!$B$20,"RECUSADO — vira carga","")) | P6: =IF($A6="","",IFERROR(PREMISSAS!$B$7*(IF($D6>=1,INDEX(TABELAS_OFICIAIS!$D$6:$F$14,MATCH(PREMISSAS!$B$11,TABELAS_OFICIAIS!$A$6:$A$14,0),1),0)+IF($D6>=2,INDEX(TABELAS_OFICIAIS!$D$6:$F$14,MATCH(PREMISSAS!$B$11,TABELAS_OFICIAIS!$A$6:$A$14,0),2),0)+IF($D6>=3,MAX(0,MIN($D6,5)-2)*INDEX(TABELAS_OFICIAIS!$D$6:$F$14,MATCH(PREMISSAS!$B$11,TABELAS_OFICIAIS!$A$6:$A$14,0),3),0)+IF(COUNTIFS($E6:$I6,">"&PREMISSAS!$B$21,$E6:$I6,"<="&PREMISSAS!$B$20)>0,COUNTIFS($E6:$I6,">"&PREMISSAS!$B$21,$E6:$I6,"<="&PREMISSAS!$B$20)*INDEX(TABELAS_OFICIAIS!$B$21:$B$23,MATCH(PREMISSAS!$B$5,TABELAS_OFICIAIS!$A$21:$A$23,0)),0)+IF($J6>0,$J6*INDEX(TABELAS_OFICIAIS!$B$27:$B$29,MATCH(PREMISSAS!$B$5,TABELAS_OFICIAIS!$A$27:$A$29,0)),0)),"n/d — cotar com a cia"))
A7: Carlos Menezes | B7: Técnico de som | C7: 10 | D7: 2 | E7: 23 | F7: 28 | J7: 0 | K7: =IF($A7="","",SUM($E7:$I7)) | L7: =IF($A7="","",IF(COUNT($E7:$I7)=0,0,MAX($E7:$I7))) | M7: =IF($A7="","",IF($C7>PREMISSAS!$B$22,"acima de "&PREMISSAS!$B$22&" kg — confira o contrato da cia","ok")) | N7: =IF($A7="","",IF($L7>PREMISSAS!$B$19,"EXCESSO","ok")) | O7: =IF($A7="","",IF($L7>PREMISSAS!$B$20,"RECUSADO — vira carga","")) | P7: =IF($A7="","",IFERROR(PREMISSAS!$B$7*(IF($D7>=1,INDEX(TABELAS_OFICIAIS!$D$6:$F$14,MATCH(PREMISSAS!$B$11,TABELAS_OFICIAIS!$A$6:$A$14,0),1),0)+IF($D7>=2,INDEX(TABELAS_OFICIAIS!$D$6:$F$14,MATCH(PREMISSAS!$B$11,TABELAS_OFICIAIS!$A$6:$A$14,0),2),0)+IF($D7>=3,MAX(0,MIN($D7,5)-2)*INDEX(TABELAS_OFICIAIS!$D$6:$F$14,MATCH(PREMISSAS!$B$11,TABELAS_OFICIAIS!$A$6:$A$14,0),3),0)+IF(COUNTIFS($E7:$I7,">"&PREMISSAS!$B$21,$E7:$I7,"<="&PREMISSAS!$B$20)>0,COUNTIFS($E7:$I7,">"&PREMISSAS!$B$21,$E7:$I7,"<="&PREMISSAS!$B$20)*INDEX(TABELAS_OFICIAIS!$B$21:$B$23,MATCH(PREMISSAS!$B$5,TABELAS_OFICIAIS!$A$21:$A$23,0)),0)+IF($J7>0,$J7*INDEX(TABELAS_OFICIAIS!$B$27:$B$29,MATCH(PREMISSAS!$B$5,TABELAS_OFICIAIS!$A$27:$A$29,0)),0)),"n/d — cotar com a cia"))
A8: Diego Alves | B8: Baterista | C8: 8 | D8: 1 | E8: 23 | J8: 1 | K8: =IF($A8="","",SUM($E8:$I8)) | L8: =IF($A8="","",IF(COUNT($E8:$I8)=0,0,MAX($E8:$I8))) | M8: =IF($A8="","",IF($C8>PREMISSAS!$B$22,"acima de "&PREMISSAS!$B$22&" kg — confira o contrato da cia","ok")) | N8: =IF($A8="","",IF($L8>PREMISSAS!$B$19,"EXCESSO","ok")) | O8: =IF($A8="","",IF($L8>PREMISSAS!$B$20,"RECUSADO — vira carga","")) | P8: =IF($A8="","",IFERROR(PREMISSAS!$B$7*(IF($D8>=1,INDEX(TABELAS_OFICIAIS!$D$6:$F$14,MATCH(PREMISSAS!$B$11,TABELAS_OFICIAIS!$A$6:$A$14,0),1),0)+IF($D8>=2,INDEX(TABELAS_OFICIAIS!$D$6:$F$14,MATCH(PREMISSAS!$B$11,TABELAS_OFICIAIS!$A$6:$A$14,0),2),0)+IF($D8>=3,MAX(0,MIN($D8,5)-2)*INDEX(TABELAS_OFICIAIS!$D$6:$F$14,MATCH(PREMISSAS!$B$11,TABELAS_OFICIAIS!$A$6:$A$14,0),3),0)+IF(COUNTIFS($E8:$I8,">"&PREMISSAS!$B$21,$E8:$I8,"<="&PREMISSAS!$B$20)>0,COUNTIFS($E8:$I8,">"&PREMISSAS!$B$21,$E8:$I8,"<="&PREMISSAS!$B$20)*INDEX(TABELAS_OFICIAIS!$B$21:$B$23,MATCH(PREMISSAS!$B$5,TABELAS_OFICIAIS!$A$21:$A$23,0)),0)+IF($J8>0,$J8*INDEX(TABELAS_OFICIAIS!$B$27:$B$29,MATCH(PREMISSAS!$B$5,TABELAS_OFICIAIS!$A$27:$A$29,0)),0)),"n/d — cotar com a cia"))
A9: Fernanda Luz | B9: Iluminadora | C9: 12 | D9: 1 | E9: 23 | J9: 0 | K9: =IF($A9="","",SUM($E9:$I9)) | L9: =IF($A9="","",IF(COUNT($E9:$I9)=0,0,MAX($E9:$I9))) | M9: =IF($A9="","",IF($C9>PREMISSAS!$B$22,"acima de "&PREMISSAS!$B$22&" kg — confira o contrato da cia","ok")) | N9: =IF($A9="","",IF($L9>PREMISSAS!$B$19,"EXCESSO","ok")) | O9: =IF($A9="","",IF($L9>PREMISSAS!$B$20,"RECUSADO — vira carga","")) | P9: =IF($A9="","",IFERROR(PREMISSAS!$B$7*(IF($D9>=1,INDEX(TABELAS_OFICIAIS!$D$6:$F$14,MATCH(PREMISSAS!$B$11,TABELAS_OFICIAIS!$A$6:$A$14,0),1),0)+IF($D9>=2,INDEX(TABELAS_OFICIAIS!$D$6:$F$14,MATCH(PREMISSAS!$B$11,TABELAS_OFICIAIS!$A$6:$A$14,0),2),0)+IF($D9>=3,MAX(0,MIN($D9,5)-2)*INDEX(TABELAS_OFICIAIS!$D$6:$F$14,MATCH(PREMISSAS!$B$11,TABELAS_OFICIAIS!$A$6:$A$14,0),3),0)+IF(COUNTIFS($E9:$I9,">"&PREMISSAS!$B$21,$E9:$I9,"<="&PREMISSAS!$B$20)>0,COUNTIFS($E9:$I9,">"&PREMISSAS!$B$21,$E9:$I9,"<="&PREMISSAS!$B$20)*INDEX(TABELAS_OFICIAIS!$B$21:$B$23,MATCH(PREMISSAS!$B$5,TABELAS_OFICIAIS!$A$21:$A$23,0)),0)+IF($J9>0,$J9*INDEX(TABELAS_OFICIAIS!$B$27:$B$29,MATCH(PREMISSAS!$B$5,TABELAS_OFICIAIS!$A$27:$A$29,0)),0)),"n/d — cotar com a cia"))
A10: Gustavo Pinto | B10: Roadie | C10: 10 | D10: 3 | E10: 23 | F10: 23 | G10: 34 | J10: 0 | K10: =IF($A10="","",SUM($E10:$I10)) | L10: =IF($A10="","",IF(COUNT($E10:$I10)=0,0,MAX($E10:$I10))) | M10: =IF($A10="","",IF($C10>PREMISSAS!$B$22,"acima de "&PREMISSAS!$B$22&" kg — confira o contrato da cia","ok")) | N10: =IF($A10="","",IF($L10>PREMISSAS!$B$19,"EXCESSO","ok")) | O10: =IF($A10="","",IF($L10>PREMISSAS!$B$20,"RECUSADO — vira carga","")) | P10: =IF($A10="","",IFERROR(PREMISSAS!$B$7*(IF($D10>=1,INDEX(TABELAS_OFICIAIS!$D$6:$F$14,MATCH(PREMISSAS!$B$11,TABELAS_OFICIAIS!$A$6:$A$14,0),1),0)+IF($D10>=2,INDEX(TABELAS_OFICIAIS!$D$6:$F$14,MATCH(PREMISSAS!$B$11,TABELAS_OFICIAIS!$A$6:$A$14,0),2),0)+IF($D10>=3,MAX(0,MIN($D10,5)-2)*INDEX(TABELAS_OFICIAIS!$D$6:$F$14,MATCH(PREMISSAS!$B$11,TABELAS_OFICIAIS!$A$6:$A$14,0),3),0)+IF(COUNTIFS($E10:$I10,">"&PREMISSAS!$B$21,$E10:$I10,"<="&PREMISSAS!$B$20)>0,COUNTIFS($E10:$I10,">"&PREMISSAS!$B$21,$E10:$I10,"<="&PREMISSAS!$B$20)*INDEX(TABELAS_OFICIAIS!$B$21:$B$23,MATCH(PREMISSAS!$B$5,TABELAS_OFICIAIS!$A$21:$A$23,0)),0)+IF($J10>0,$J10*INDEX(TABELAS_OFICIAIS!$B$27:$B$29,MATCH(PREMISSAS!$B$5,TABELAS_OFICIAIS!$A$27:$A$29,0)),0)),"n/d — cotar com a cia"))
A11: Helena Braga | B11: Backing vocal | C11: 7 | D11: 1 | E11: 18 | J11: 0 | K11: =IF($A11="","",SUM($E11:$I11)) | L11: =IF($A11="","",IF(COUNT($E11:$I11)=0,0,MAX($E11:$I11))) | M11: =IF($A11="","",IF($C11>PREMISSAS!$B$22,"acima de "&PREMISSAS!$B$22&" kg — confira o contrato da cia","ok")) | N11: =IF($A11="","",IF($L11>PREMISSAS!$B$19,"EXCESSO","ok")) | O11: =IF($A11="","",IF($L11>PREMISSAS!$B$20,"RECUSADO — vira carga","")) | P11: =IF($A11="","",IFERROR(PREMISSAS!$B$7*(IF($D11>=1,INDEX(TABELAS_OFICIAIS!$D$6:$F$14,MATCH(PREMISSAS!$B$11,TABELAS_OFICIAIS!$A$6:$A$14,0),1),0)+IF($D11>=2,INDEX(TABELAS_OFICIAIS!$D$6:$F$14,MATCH(PREMISSAS!$B$11,TABELAS_OFICIAIS!$A$6:$A$14,0),2),0)+IF($D11>=3,MAX(0,MIN($D11,5)-2)*INDEX(TABELAS_OFICIAIS!$D$6:$F$14,MATCH(PREMISSAS!$B$11,TABELAS_OFICIAIS!$A$6:$A$14,0),3),0)+IF(COUNTIFS($E11:$I11,">"&PREMISSAS!$B$21,$E11:$I11,"<="&PREMISSAS!$B$20)>0,COUNTIFS($E11:$I11,">"&PREMISSAS!$B$21,$E11:$I11,"<="&PREMISSAS!$B$20)*INDEX(TABELAS_OFICIAIS!$B$21:$B$23,MATCH(PREMISSAS!$B$5,TABELAS_OFICIAIS!$A$21:$A$23,0)),0)+IF($J11>0,$J11*INDEX(TABELAS_OFICIAIS!$B$27:$B$29,MATCH(PREMISSAS!$B$5,TABELAS_OFICIAIS!$A$27:$A$29,0)),0)),"n/d — cotar com a cia"))
A12: Ivan Cordeiro | B12: Contrabaixista | C12: 9 | D12: 1 | E12: 23 | J12: 1 | K12: =IF($A12="","",SUM($E12:$I12)) | L12: =IF($A12="","",IF(COUNT($E12:$I12)=0,0,MAX($E12:$I12))) | M12: =IF($A12="","",IF($C12>PREMISSAS!$B$22,"acima de "&PREMISSAS!$B$22&" kg — confira o contrato da cia","ok")) | N12: =IF($A12="","",IF($L12>PREMISSAS!$B$19,"EXCESSO","ok")) | O12: =IF($A12="","",IF($L12>PREMISSAS!$B$20,"RECUSADO — vira carga","")) | P12: =IF($A12="","",IFERROR(PREMISSAS!$B$7*(IF($D12>=1,INDEX(TABELAS_OFICIAIS!$D$6:$F$14,MATCH(PREMISSAS!$B$11,TABELAS_OFICIAIS!$A$6:$A$14,0),1),0)+IF($D12>=2,INDEX(TABELAS_OFICIAIS!$D$6:$F$14,MATCH(PREMISSAS!$B$11,TABELAS_OFICIAIS!$A$6:$A$14,0),2),0)+IF($D12>=3,MAX(0,MIN($D12,5)-2)*INDEX(TABELAS_OFICIAIS!$D$6:$F$14,MATCH(PREMISSAS!$B$11,TABELAS_OFICIAIS!$A$6:$A$14,0),3),0)+IF(COUNTIFS($E12:$I12,">"&PREMISSAS!$B$21,$E12:$I12,"<="&PREMISSAS!$B$20)>0,COUNTIFS($E12:$I12,">"&PREMISSAS!$B$21,$E12:$I12,"<="&PREMISSAS!$B$20)*INDEX(TABELAS_OFICIAIS!$B$21:$B$23,MATCH(PREMISSAS!$B$5,TABELAS_OFICIAIS!$A$21:$A$23,0)),0)+IF($J12>0,$J12*INDEX(TABELAS_OFICIAIS!$B$27:$B$29,MATCH(PREMISSAS!$B$5,TABELAS_OFICIAIS!$A$27:$A$29,0)),0)),"n/d — cotar com a cia"))
A13: Júlia Prado | B13: Assistente de palco | C13: 8 | D13: 1 | E13: 21 | J13: 0 | K13: =IF($A13="","",SUM($E13:$I13)) | L13: =IF($A13="","",IF(COUNT($E13:$I13)=0,0,MAX($E13:$I13))) | M13: =IF($A13="","",IF($C13>PREMISSAS!$B$22,"acima de "&PREMISSAS!$B$22&" kg — confira o contrato da cia","ok")) | N13: =IF($A13="","",IF($L13>PREMISSAS!$B$19,"EXCESSO","ok")) | O13: =IF($A13="","",IF($L13>PREMISSAS!$B$20,"RECUSADO — vira carga","")) | P13: =IF($A13="","",IFERROR(PREMISSAS!$B$7*(IF($D13>=1,INDEX(TABELAS_OFICIAIS!$D$6:$F$14,MATCH(PREMISSAS!$B$11,TABELAS_OFICIAIS!$A$6:$A$14,0),1),0)+IF($D13>=2,INDEX(TABELAS_OFICIAIS!$D$6:$F$14,MATCH(PREMISSAS!$B$11,TABELAS_OFICIAIS!$A$6:$A$14,0),2),0)+IF($D13>=3,MAX(0,MIN($D13,5)-2)*INDEX(TABELAS_OFICIAIS!$D$6:$F$14,MATCH(PREMISSAS!$B$11,TABELAS_OFICIAIS!$A$6:$A$14,0),3),0)+IF(COUNTIFS($E13:$I13,">"&PREMISSAS!$B$21,$E13:$I13,"<="&PREMISSAS!$B$20)>0,COUNTIFS($E13:$I13,">"&PREMISSAS!$B$21,$E13:$I13,"<="&PREMISSAS!$B$20)*INDEX(TABELAS_OFICIAIS!$B$21:$B$23,MATCH(PREMISSAS!$B$5,TABELAS_OFICIAIS!$A$21:$A$23,0)),0)+IF($J13>0,$J13*INDEX(TABELAS_OFICIAIS!$B$27:$B$29,MATCH(PREMISSAS!$B$5,TABELAS_OFICIAIS!$A$27:$A$29,0)),0)),"n/d — cotar com a cia"))
K14: =IF($A14="","",SUM($E14:$I14)) | L14: =IF($A14="","",IF(COUNT($E14:$I14)=0,0,MAX($E14:$I14))) | M14: =IF($A14="","",IF($C14>PREMISSAS!$B$22,"acima de "&PREMISSAS!$B$22&" kg — confira o contrato da cia","ok")) | N14: =IF($A14="","",IF($L14>PREMISSAS!$B$19,"EXCESSO","ok")) | O14: =IF($A14="","",IF($L14>PREMISSAS!$B$20,"RECUSADO — vira carga","")) | P14: =IF($A14="","",IFERROR(PREMISSAS!$B$7*(IF($D14>=1,INDEX(TABELAS_OFICIAIS!$D$6:$F$14,MATCH(PREMISSAS!$B$11,TABELAS_OFICIAIS!$A$6:$A$14,0),1),0)+IF($D14>=2,INDEX(TABELAS_OFICIAIS!$D$6:$F$14,MATCH(PREMISSAS!$B$11,TABELAS_OFICIAIS!$A$6:$A$14,0),2),0)+IF($D14>=3,MAX(0,MIN($D14,5)-2)*INDEX(TABELAS_OFICIAIS!$D$6:$F$14,MATCH(PREMISSAS!$B$11,TABELAS_OFICIAIS!$A$6:$A$14,0),3),0)+IF(COUNTIFS($E14:$I14,">"&PREMISSAS!$B$21,$E14:$I14,"<="&PREMISSAS!$B$20)>0,COUNTIFS($E14:$I14,">"&PREMISSAS!$B$21,$E14:$I14,"<="&PREMISSAS!$B$20)*INDEX(TABELAS_OFICIAIS!$B$21:$B$23,MATCH(PREMISSAS!$B$5,TABELAS_OFICIAIS!$A$21:$A$23,0)),0)+IF($J14>0,$J14*INDEX(TABELAS_OFICIAIS!$B$27:$B$29,MATCH(PREMISSAS!$B$5,TABELAS_OFICIAIS!$A$27:$A$29,0)),0)),"n/d — cotar com a cia"))
K15: =IF($A15="","",SUM($E15:$I15)) | L15: =IF($A15="","",IF(COUNT($E15:$I15)=0,0,MAX($E15:$I15))) | M15: =IF($A15="","",IF($C15>PREMISSAS!$B$22,"acima de "&PREMISSAS!$B$22&" kg — confira o contrato da cia","ok")) | N15: =IF($A15="","",IF($L15>PREMISSAS!$B$19,"EXCESSO","ok")) | O15: =IF($A15="","",IF($L15>PREMISSAS!$B$20,"RECUSADO — vira carga","")) | P15: =IF($A15="","",IFERROR(PREMISSAS!$B$7*(IF($D15>=1,INDEX(TABELAS_OFICIAIS!$D$6:$F$14,MATCH(PREMISSAS!$B$11,TABELAS_OFICIAIS!$A$6:$A$14,0),1),0)+IF($D15>=2,INDEX(TABELAS_OFICIAIS!$D$6:$F$14,MATCH(PREMISSAS!$B$11,TABELAS_OFICIAIS!$A$6:$A$14,0),2),0)+IF($D15>=3,MAX(0,MIN($D15,5)-2)*INDEX(TABELAS_OFICIAIS!$D$6:$F$14,MATCH(PREMISSAS!$B$11,TABELAS_OFICIAIS!$A$6:$A$14,0),3),0)+IF(COUNTIFS($E15:$I15,">"&PREMISSAS!$B$21,$E15:$I15,"<="&PREMISSAS!$B$20)>0,COUNTIFS($E15:$I15,">"&PREMISSAS!$B$21,$E15:$I15,"<="&PREMISSAS!$B$20)*INDEX(TABELAS_OFICIAIS!$B$21:$B$23,MATCH(PREMISSAS!$B$5,TABELAS_OFICIAIS!$A$21:$A$23,0)),0)+IF($J15>0,$J15*INDEX(TABELAS_OFICIAIS!$B$27:$B$29,MATCH(PREMISSAS!$B$5,TABELAS_OFICIAIS!$A$27:$A$29,0)),0)),"n/d — cotar com a cia"))
K16: =IF($A16="","",SUM($E16:$I16)) | L16: =IF($A16="","",IF(COUNT($E16:$I16)=0,0,MAX($E16:$I16))) | M16: =IF($A16="","",IF($C16>PREMISSAS!$B$22,"acima de "&PREMISSAS!$B$22&" kg — confira o contrato da cia","ok")) | N16: =IF($A16="","",IF($L16>PREMISSAS!$B$19,"EXCESSO","ok")) | O16: =IF($A16="","",IF($L16>PREMISSAS!$B$20,"RECUSADO — vira carga","")) | P16: =IF($A16="","",IFERROR(PREMISSAS!$B$7*(IF($D16>=1,INDEX(TABELAS_OFICIAIS!$D$6:$F$14,MATCH(PREMISSAS!$B$11,TABELAS_OFICIAIS!$A$6:$A$14,0),1),0)+IF($D16>=2,INDEX(TABELAS_OFICIAIS!$D$6:$F$14,MATCH(PREMISSAS!$B$11,TABELAS_OFICIAIS!$A$6:$A$14,0),2),0)+IF($D16>=3,MAX(0,MIN($D16,5)-2)*INDEX(TABELAS_OFICIAIS!$D$6:$F$14,MATCH(PREMISSAS!$B$11,TABELAS_OFICIAIS!$A$6:$A$14,0),3),0)+IF(COUNTIFS($E16:$I16,">"&PREMISSAS!$B$21,$E16:$I16,"<="&PREMISSAS!$B$20)>0,COUNTIFS($E16:$I16,">"&PREMISSAS!$B$21,$E16:$I16,"<="&PREMISSAS!$B$20)*INDEX(TABELAS_OFICIAIS!$B$21:$B$23,MATCH(PREMISSAS!$B$5,TABELAS_OFICIAIS!$A$21:$A$23,0)),0)+IF($J16>0,$J16*INDEX(TABELAS_OFICIAIS!$B$27:$B$29,MATCH(PREMISSAS!$B$5,TABELAS_OFICIAIS!$A$27:$A$29,0)),0)),"n/d — cotar com a cia"))
K17: =IF($A17="","",SUM($E17:$I17)) | L17: =IF($A17="","",IF(COUNT($E17:$I17)=0,0,MAX($E17:$I17))) | M17: =IF($A17="","",IF($C17>PREMISSAS!$B$22,"acima de "&PREMISSAS!$B$22&" kg — confira o contrato da cia","ok")) | N17: =IF($A17="","",IF($L17>PREMISSAS!$B$19,"EXCESSO","ok")) | O17: =IF($A17="","",IF($L17>PREMISSAS!$B$20,"RECUSADO — vira carga","")) | P17: =IF($A17="","",IFERROR(PREMISSAS!$B$7*(IF($D17>=1,INDEX(TABELAS_OFICIAIS!$D$6:$F$14,MATCH(PREMISSAS!$B$11,TABELAS_OFICIAIS!$A$6:$A$14,0),1),0)+IF($D17>=2,INDEX(TABELAS_OFICIAIS!$D$6:$F$14,MATCH(PREMISSAS!$B$11,TABELAS_OFICIAIS!$A$6:$A$14,0),2),0)+IF($D17>=3,MAX(0,MIN($D17,5)-2)*INDEX(TABELAS_OFICIAIS!$D$6:$F$14,MATCH(PREMISSAS!$B$11,TABELAS_OFICIAIS!$A$6:$A$14,0),3),0)+IF(COUNTIFS($E17:$I17,">"&PREMISSAS!$B$21,$E17:$I17,"<="&PREMISSAS!$B$20)>0,COUNTIFS($E17:$I17,">"&PREMISSAS!$B$21,$E17:$I17,"<="&PREMISSAS!$B$20)*INDEX(TABELAS_OFICIAIS!$B$21:$B$23,MATCH(PREMISSAS!$B$5,TABELAS_OFICIAIS!$A$21:$A$23,0)),0)+IF($J17>0,$J17*INDEX(TABELAS_OFICIAIS!$B$27:$B$29,MATCH(PREMISSAS!$B$5,TABELAS_OFICIAIS!$A$27:$A$29,0)),0)),"n/d — cotar com a cia"))
K18: =IF($A18="","",SUM($E18:$I18)) | L18: =IF($A18="","",IF(COUNT($E18:$I18)=0,0,MAX($E18:$I18))) | M18: =IF($A18="","",IF($C18>PREMISSAS!$B$22,"acima de "&PREMISSAS!$B$22&" kg — confira o contrato da cia","ok")) | N18: =IF($A18="","",IF($L18>PREMISSAS!$B$19,"EXCESSO","ok")) | O18: =IF($A18="","",IF($L18>PREMISSAS!$B$20,"RECUSADO — vira carga","")) | P18: =IF($A18="","",IFERROR(PREMISSAS!$B$7*(IF($D18>=1,INDEX(TABELAS_OFICIAIS!$D$6:$F$14,MATCH(PREMISSAS!$B$11,TABELAS_OFICIAIS!$A$6:$A$14,0),1),0)+IF($D18>=2,INDEX(TABELAS_OFICIAIS!$D$6:$F$14,MATCH(PREMISSAS!$B$11,TABELAS_OFICIAIS!$A$6:$A$14,0),2),0)+IF($D18>=3,MAX(0,MIN($D18,5)-2)*INDEX(TABELAS_OFICIAIS!$D$6:$F$14,MATCH(PREMISSAS!$B$11,TABELAS_OFICIAIS!$A$6:$A$14,0),3),0)+IF(COUNTIFS($E18:$I18,">"&PREMISSAS!$B$21,$E18:$I18,"<="&PREMISSAS!$B$20)>0,COUNTIFS($E18:$I18,">"&PREMISSAS!$B$21,$E18:$I18,"<="&PREMISSAS!$B$20)*INDEX(TABELAS_OFICIAIS!$B$21:$B$23,MATCH(PREMISSAS!$B$5,TABELAS_OFICIAIS!$A$21:$A$23,0)),0)+IF($J18>0,$J18*INDEX(TABELAS_OFICIAIS!$B$27:$B$29,MATCH(PREMISSAS!$B$5,TABELAS_OFICIAIS!$A$27:$A$29,0)),0)),"n/d — cotar com a cia"))
K19: =IF($A19="","",SUM($E19:$I19)) | L19: =IF($A19="","",IF(COUNT($E19:$I19)=0,0,MAX($E19:$I19))) | M19: =IF($A19="","",IF($C19>PREMISSAS!$B$22,"acima de "&PREMISSAS!$B$22&" kg — confira o contrato da cia","ok")) | N19: =IF($A19="","",IF($L19>PREMISSAS!$B$19,"EXCESSO","ok")) | O19: =IF($A19="","",IF($L19>PREMISSAS!$B$20,"RECUSADO — vira carga","")) | P19: =IF($A19="","",IFERROR(PREMISSAS!$B$7*(IF($D19>=1,INDEX(TABELAS_OFICIAIS!$D$6:$F$14,MATCH(PREMISSAS!$B$11,TABELAS_OFICIAIS!$A$6:$A$14,0),1),0)+IF($D19>=2,INDEX(TABELAS_OFICIAIS!$D$6:$F$14,MATCH(PREMISSAS!$B$11,TABELAS_OFICIAIS!$A$6:$A$14,0),2),0)+IF($D19>=3,MAX(0,MIN($D19,5)-2)*INDEX(TABELAS_OFICIAIS!$D$6:$F$14,MATCH(PREMISSAS!$B$11,TABELAS_OFICIAIS!$A$6:$A$14,0),3),0)+IF(COUNTIFS($E19:$I19,">"&PREMISSAS!$B$21,$E19:$I19,"<="&PREMISSAS!$B$20)>0,COUNTIFS($E19:$I19,">"&PREMISSAS!$B$21,$E19:$I19,"<="&PREMISSAS!$B$20)*INDEX(TABELAS_OFICIAIS!$B$21:$B$23,MATCH(PREMISSAS!$B$5,TABELAS_OFICIAIS!$A$21:$A$23,0)),0)+IF($J19>0,$J19*INDEX(TABELAS_OFICIAIS!$B$27:$B$29,MATCH(PREMISSAS!$B$5,TABELAS_OFICIAIS!$A$27:$A$29,0)),0)),"n/d — cotar com a cia"))
K20: =IF($A20="","",SUM($E20:$I20)) | L20: =IF($A20="","",IF(COUNT($E20:$I20)=0,0,MAX($E20:$I20))) | M20: =IF($A20="","",IF($C20>PREMISSAS!$B$22,"acima de "&PREMISSAS!$B$22&" kg — confira o contrato da cia","ok")) | N20: =IF($A20="","",IF($L20>PREMISSAS!$B$19,"EXCESSO","ok")) | O20: =IF($A20="","",IF($L20>PREMISSAS!$B$20,"RECUSADO — vira carga","")) | P20: =IF($A20="","",IFERROR(PREMISSAS!$B$7*(IF($D20>=1,INDEX(TABELAS_OFICIAIS!$D$6:$F$14,MATCH(PREMISSAS!$B$11,TABELAS_OFICIAIS!$A$6:$A$14,0),1),0)+IF($D20>=2,INDEX(TABELAS_OFICIAIS!$D$6:$F$14,MATCH(PREMISSAS!$B$11,TABELAS_OFICIAIS!$A$6:$A$14,0),2),0)+IF($D20>=3,MAX(0,MIN($D20,5)-2)*INDEX(TABELAS_OFICIAIS!$D$6:$F$14,MATCH(PREMISSAS!$B$11,TABELAS_OFICIAIS!$A$6:$A$14,0),3),0)+IF(COUNTIFS($E20:$I20,">"&PREMISSAS!$B$21,$E20:$I20,"<="&PREMISSAS!$B$20)>0,COUNTIFS($E20:$I20,">"&PREMISSAS!$B$21,$E20:$I20,"<="&PREMISSAS!$B$20)*INDEX(TABELAS_OFICIAIS!$B$21:$B$23,MATCH(PREMISSAS!$B$5,TABELAS_OFICIAIS!$A$21:$A$23,0)),0)+IF($J20>0,$J20*INDEX(TABELAS_OFICIAIS!$B$27:$B$29,MATCH(PREMISSAS!$B$5,TABELAS_OFICIAIS!$A$27:$A$29,0)),0)),"n/d — cotar com a cia"))
K21: =IF($A21="","",SUM($E21:$I21)) | L21: =IF($A21="","",IF(COUNT($E21:$I21)=0,0,MAX($E21:$I21))) | M21: =IF($A21="","",IF($C21>PREMISSAS!$B$22,"acima de "&PREMISSAS!$B$22&" kg — confira o contrato da cia","ok")) | N21: =IF($A21="","",IF($L21>PREMISSAS!$B$19,"EXCESSO","ok")) | O21: =IF($A21="","",IF($L21>PREMISSAS!$B$20,"RECUSADO — vira carga","")) | P21: =IF($A21="","",IFERROR(PREMISSAS!$B$7*(IF($D21>=1,INDEX(TABELAS_OFICIAIS!$D$6:$F$14,MATCH(PREMISSAS!$B$11,TABELAS_OFICIAIS!$A$6:$A$14,0),1),0)+IF($D21>=2,INDEX(TABELAS_OFICIAIS!$D$6:$F$14,MATCH(PREMISSAS!$B$11,TABELAS_OFICIAIS!$A$6:$A$14,0),2),0)+IF($D21>=3,MAX(0,MIN($D21,5)-2)*INDEX(TABELAS_OFICIAIS!$D$6:$F$14,MATCH(PREMISSAS!$B$11,TABELAS_OFICIAIS!$A$6:$A$14,0),3),0)+IF(COUNTIFS($E21:$I21,">"&PREMISSAS!$B$21,$E21:$I21,"<="&PREMISSAS!$B$20)>0,COUNTIFS($E21:$I21,">"&PREMISSAS!$B$21,$E21:$I21,"<="&PREMISSAS!$B$20)*INDEX(TABELAS_OFICIAIS!$B$21:$B$23,MATCH(PREMISSAS!$B$5,TABELAS_OFICIAIS!$A$21:$A$23,0)),0)+IF($J21>0,$J21*INDEX(TABELAS_OFICIAIS!$B$27:$B$29,MATCH(PREMISSAS!$B$5,TABELAS_OFICIAIS!$A$27:$A$29,0)),0)),"n/d — cotar com a cia"))
K22: =IF($A22="","",SUM($E22:$I22)) | L22: =IF($A22="","",IF(COUNT($E22:$I22)=0,0,MAX($E22:$I22))) | M22: =IF($A22="","",IF($C22>PREMISSAS!$B$22,"acima de "&PREMISSAS!$B$22&" kg — confira o contrato da cia","ok")) | N22: =IF($A22="","",IF($L22>PREMISSAS!$B$19,"EXCESSO","ok")) | O22: =IF($A22="","",IF($L22>PREMISSAS!$B$20,"RECUSADO — vira carga","")) | P22: =IF($A22="","",IFERROR(PREMISSAS!$B$7*(IF($D22>=1,INDEX(TABELAS_OFICIAIS!$D$6:$F$14,MATCH(PREMISSAS!$B$11,TABELAS_OFICIAIS!$A$6:$A$14,0),1),0)+IF($D22>=2,INDEX(TABELAS_OFICIAIS!$D$6:$F$14,MATCH(PREMISSAS!$B$11,TABELAS_OFICIAIS!$A$6:$A$14,0),2),0)+IF($D22>=3,MAX(0,MIN($D22,5)-2)*INDEX(TABELAS_OFICIAIS!$D$6:$F$14,MATCH(PREMISSAS!$B$11,TABELAS_OFICIAIS!$A$6:$A$14,0),3),0)+IF(COUNTIFS($E22:$I22,">"&PREMISSAS!$B$21,$E22:$I22,"<="&PREMISSAS!$B$20)>0,COUNTIFS($E22:$I22,">"&PREMISSAS!$B$21,$E22:$I22,"<="&PREMISSAS!$B$20)*INDEX(TABELAS_OFICIAIS!$B$21:$B$23,MATCH(PREMISSAS!$B$5,TABELAS_OFICIAIS!$A$21:$A$23,0)),0)+IF($J22>0,$J22*INDEX(TABELAS_OFICIAIS!$B$27:$B$29,MATCH(PREMISSAS!$B$5,TABELAS_OFICIAIS!$A$27:$A$29,0)),0)),"n/d — cotar com a cia"))
K23: =IF($A23="","",SUM($E23:$I23)) | L23: =IF($A23="","",IF(COUNT($E23:$I23)=0,0,MAX($E23:$I23))) | M23: =IF($A23="","",IF($C23>PREMISSAS!$B$22,"acima de "&PREMISSAS!$B$22&" kg — confira o contrato da cia","ok")) | N23: =IF($A23="","",IF($L23>PREMISSAS!$B$19,"EXCESSO","ok")) | O23: =IF($A23="","",IF($L23>PREMISSAS!$B$20,"RECUSADO — vira carga","")) | P23: =IF($A23="","",IFERROR(PREMISSAS!$B$7*(IF($D23>=1,INDEX(TABELAS_OFICIAIS!$D$6:$F$14,MATCH(PREMISSAS!$B$11,TABELAS_OFICIAIS!$A$6:$A$14,0),1),0)+IF($D23>=2,INDEX(TABELAS_OFICIAIS!$D$6:$F$14,MATCH(PREMISSAS!$B$11,TABELAS_OFICIAIS!$A$6:$A$14,0),2),0)+IF($D23>=3,MAX(0,MIN($D23,5)-2)*INDEX(TABELAS_OFICIAIS!$D$6:$F$14,MATCH(PREMISSAS!$B$11,TABELAS_OFICIAIS!$A$6:$A$14,0),3),0)+IF(COUNTIFS($E23:$I23,">"&PREMISSAS!$B$21,$E23:$I23,"<="&PREMISSAS!$B$20)>0,COUNTIFS($E23:$I23,">"&PREMISSAS!$B$21,$E23:$I23,"<="&PREMISSAS!$B$20)*INDEX(TABELAS_OFICIAIS!$B$21:$B$23,MATCH(PREMISSAS!$B$5,TABELAS_OFICIAIS!$A$21:$A$23,0)),0)+IF($J23>0,$J23*INDEX(TABELAS_OFICIAIS!$B$27:$B$29,MATCH(PREMISSAS!$B$5,TABELAS_OFICIAIS!$A$27:$A$29,0)),0)),"n/d — cotar com a cia"))
K24: =IF($A24="","",SUM($E24:$I24)) | L24: =IF($A24="","",IF(COUNT($E24:$I24)=0,0,MAX($E24:$I24))) | M24: =IF($A24="","",IF($C24>PREMISSAS!$B$22,"acima de "&PREMISSAS!$B$22&" kg — confira o contrato da cia","ok")) | N24: =IF($A24="","",IF($L24>PREMISSAS!$B$19,"EXCESSO","ok")) | O24: =IF($A24="","",IF($L24>PREMISSAS!$B$20,"RECUSADO — vira carga","")) | P24: =IF($A24="","",IFERROR(PREMISSAS!$B$7*(IF($D24>=1,INDEX(TABELAS_OFICIAIS!$D$6:$F$14,MATCH(PREMISSAS!$B$11,TABELAS_OFICIAIS!$A$6:$A$14,0),1),0)+IF($D24>=2,INDEX(TABELAS_OFICIAIS!$D$6:$F$14,MATCH(PREMISSAS!$B$11,TABELAS_OFICIAIS!$A$6:$A$14,0),2),0)+IF($D24>=3,MAX(0,MIN($D24,5)-2)*INDEX(TABELAS_OFICIAIS!$D$6:$F$14,MATCH(PREMISSAS!$B$11,TABELAS_OFICIAIS!$A$6:$A$14,0),3),0)+IF(COUNTIFS($E24:$I24,">"&PREMISSAS!$B$21,$E24:$I24,"<="&PREMISSAS!$B$20)>0,COUNTIFS($E24:$I24,">"&PREMISSAS!$B$21,$E24:$I24,"<="&PREMISSAS!$B$20)*INDEX(TABELAS_OFICIAIS!$B$21:$B$23,MATCH(PREMISSAS!$B$5,TABELAS_OFICIAIS!$A$21:$A$23,0)),0)+IF($J24>0,$J24*INDEX(TABELAS_OFICIAIS!$B$27:$B$29,MATCH(PREMISSAS!$B$5,TABELAS_OFICIAIS!$A$27:$A$29,0)),0)),"n/d — cotar com a cia"))
K25: =IF($A25="","",SUM($E25:$I25)) | L25: =IF($A25="","",IF(COUNT($E25:$I25)=0,0,MAX($E25:$I25))) | M25: =IF($A25="","",IF($C25>PREMISSAS!$B$22,"acima de "&PREMISSAS!$B$22&" kg — confira o contrato da cia","ok")) | N25: =IF($A25="","",IF($L25>PREMISSAS!$B$19,"EXCESSO","ok")) | O25: =IF($A25="","",IF($L25>PREMISSAS!$B$20,"RECUSADO — vira carga","")) | P25: =IF($A25="","",IFERROR(PREMISSAS!$B$7*(IF($D25>=1,INDEX(TABELAS_OFICIAIS!$D$6:$F$14,MATCH(PREMISSAS!$B$11,TABELAS_OFICIAIS!$A$6:$A$14,0),1),0)+IF($D25>=2,INDEX(TABELAS_OFICIAIS!$D$6:$F$14,MATCH(PREMISSAS!$B$11,TABELAS_OFICIAIS!$A$6:$A$14,0),2),0)+IF($D25>=3,MAX(0,MIN($D25,5)-2)*INDEX(TABELAS_OFICIAIS!$D$6:$F$14,MATCH(PREMISSAS!$B$11,TABELAS_OFICIAIS!$A$6:$A$14,0),3),0)+IF(COUNTIFS($E25:$I25,">"&PREMISSAS!$B$21,$E25:$I25,"<="&PREMISSAS!$B$20)>0,COUNTIFS($E25:$I25,">"&PREMISSAS!$B$21,$E25:$I25,"<="&PREMISSAS!$B$20)*INDEX(TABELAS_OFICIAIS!$B$21:$B$23,MATCH(PREMISSAS!$B$5,TABELAS_OFICIAIS!$A$21:$A$23,0)),0)+IF($J25>0,$J25*INDEX(TABELAS_OFICIAIS!$B$27:$B$29,MATCH(PREMISSAS!$B$5,TABELAS_OFICIAIS!$A$27:$A$29,0)),0)),"n/d — cotar com a cia"))
... K45: =IF($A45="","",SUM($E45:$I45)) | L45: =IF($A45="","",IF(COUNT($E45:$I45)=0,0,MAX($E45:$I45))) | M45: =IF($A45="","",IF($C45>PREMISSAS!$B$22,"acima de "&PREMISSAS!$B$22&" kg — confira o contrato da cia","ok")) | N45: =IF($A45="","",IF($L45>PREMISSAS!$B$19,"EXCESSO","ok")) | O45: =IF($A45="","",IF($L45>PREMISSAS!$B$20,"RECUSADO — vira carga","")) | P45: =IF($A45="","",IFERROR(PREMISSAS!$B$7*(IF($D45>=1,INDEX(TABELAS_OFICIAIS!$D$6:$F$14,MATCH(PREMISSAS!$B$11,TABELAS_OFICIAIS!$A$6:$A$14,0),1),0)+IF($D45>=2,INDEX(TABELAS_OFICIAIS!$D$6:$F$14,MATCH(PREMISSAS!$B$11,TABELAS_OFICIAIS!$A$6:$A$14,0),2),0)+IF($D45>=3,MAX(0,MIN($D45,5)-2)*INDEX(TABELAS_OFICIAIS!$D$6:$F$14,MATCH(PREMISSAS!$B$11,TABELAS_OFICIAIS!$A$6:$A$14,0),3),0)+IF(COUNTIFS($E45:$I45,">"&PREMISSAS!$B$21,$E45:$I45,"<="&PREMISSAS!$B$20)>0,COUNTIFS($E45:$I45,">"&PREMISSAS!$B$21,$E45:$I45,"<="&PREMISSAS!$B$20)*INDEX(TABELAS_OFICIAIS!$B$21:$B$23,MATCH(PREMISSAS!$B$5,TABELAS_OFICIAIS!$A$21:$A$23,0)),0)+IF($J45>0,$J45*INDEX(TABELAS_OFICIAIS!$B$27:$B$29,MATCH(PREMISSAS!$B$5,TABELAS_OFICIAIS!$A$27:$A$29,0)),0)),"n/d — cotar com a cia"))

Sheet RESUMO
A1: RESUMO DA BAGAGEM DA COMITIVA
A2: Tudo aqui é fórmula sobre a aba COMITIVA, com folga até a linha 45 — acrescente gente lá e este resumo acompanha sozinho.
A4: Indicador | B4: Valor | C4: Unidade | D4: Observação
A5: Pessoas na comitiva | B5: =COUNTA(COMITIVA!$A$6:$A$45) | C5: pessoas | D5: Conta os nomes preenchidos. É a mesma célula de PREMISSAS!B10.
A6: Volumes despachados (por trecho) | B6: =SUM(COMITIVA!$D$6:$D$45) | C6: volumes
A7: Volumes despachados (ida + volta) | B7: =SUM(COMITIVA!$D$6:$D$45)*PREMISSAS!$B$7 | C7: volumes | D7: Bagagem se paga POR TRECHO.
A8: Volumes especiais / case rígido (por trecho) | B8: =SUM(COMITIVA!$J$6:$J$45) | C8: volumes | D8: GOL R$ 195 (até 292 cm) | Azul R$ 250 (acima de 158 cm) | LATAM não publica.
A9: Peso total despachado (por trecho) | B9: =SUM(COMITIVA!$K$6:$K$45) | C9: kg
A10: Peso total de mala de mão | B10: =SUM(COMITIVA!$C$6:$C$45) | C10: kg | D10: Franquia mínima de 10 kg por pessoa (Res. ANAC 400/2016, art. 14).
A11: Peso médio por volume despachado | B11: =IFERROR(SUM(COMITIVA!$K$6:$K$45)/SUM(COMITIVA!$D$6:$D$45),0) | C11: kg | D11: Acima de 23 kg você já paga excesso em algum volume.
A12: Volume mais pesado da comitiva | B12: =IFERROR(MAX(COMITIVA!$E$6:$I$45),0) | C12: kg | D12: Se passar de 45 kg, a cia recusa: vira contrato de carga.
A14: CUSTO
A15: CUSTO TOTAL DA BAGAGEM (ida + volta) | B15: =SUM(COMITIVA!$P$6:$P$45) | C15: R$ | D15: SOMA(COMITIVA!P6:P45) — com folga até a linha 45 de propósito. A SOMA ignora texto em silêncio: se a cia não publicar preço, o alerta abaixo é o que te salva.
A16: Custo médio de bagagem por pessoa | B16: =IFERROR(SUM(COMITIVA!$P$6:$P$45)/COUNTA(COMITIVA!$A$6:$A$45),0) | C16: R$
A17: Custo médio por volume despachado | B17: =IFERROR(SUM(COMITIVA!$P$6:$P$45)/(SUM(COMITIVA!$D$6:$D$45)*PREMISSAS!$B$7),0) | C17: R$ | D17: Compare com o preço da 1ª peça: se estiver bem acima, você está pagando excesso e não percebeu.
A18: Custo se TODO mundo despachasse 1 peça só, sem excesso e sem especial | B18: =IFERROR(COUNTA(COMITIVA!$A$6:$A$45)*PREMISSAS!$B$12*PREMISSAS!$B$7,0) | C18: R$ | D18: É o piso teórico da comitiva. A diferença para a linha 15 é o que a bagagem extra, o excesso e o case rígido custam de verdade.
A19: Quanto a bagagem extra está custando além do piso | B19: =IFERROR(SUM(COMITIVA!$P$6:$P$45)-$B$18,0) | C19: R$ | D19: Se este número te assusta, é porque ele deveria ter aparecido no orçamento — e não na fatura.
A20: ALERTAS
A21: Nº de volumes com EXCESSO (acima de 23 kg) | B21: =COUNTIF(COMITIVA!$N$6:$N$45,"EXCESSO") | C21: pessoas | D21: Conta PESSOAS cujo volume mais pesado passa de 23 kg.
A22: Nº de volumes RECUSADOS (acima de 45 kg) | B22: =COUNTIF(COMITIVA!$O$6:$O$45,"RECUSADO — vira carga") | C22: pessoas | D22: Acima de 45 kg não é bagagem: é carga. Res. ANAC 400/2016, art. 15.
A23: Nº de pessoas com mala de mão acima de 10 kg | B23: =COUNTIF(COMITIVA!$C$6:$C$45,">"&PREMISSAS!$B$22) | C23: pessoas | D23: 10 kg é a franquia MÍNIMA da norma. Acima disso depende do contrato da cia — confira antes.
A24: Total de alertas | B24: =$B$21+$B$22+$B$23 | C24: alertas | D24: Zero é a meta. Não é decoração.
A26: =IF(COUNTIF(COMITIVA!$P$6:$P$45,"n/d — cotar com a cia")>0,"⚠ A companhia escolhida NÃO publica preço de despacho. A SOMA da linha 15 está ignorando essas linhas em SILÊNCIO — o total está mais baixo que a realidade. Cote com a cia antes de fechar.","ok — todos os itens têm preço oficial publicado")
A27: =IF($B$22>0,"⛔ Há volume acima de 45 kg. Isso não embarca como bagagem: a companhia recusa ou submete a contrato de transporte de CARGA (Res. ANAC 400/2016, art. 15). Replaneje ou mande de carga.","")
A28: =IF($B$21>0,"⚠ Há volume na faixa acima de 23 kg. Entre 23 e 32 kg a GOL tem DUAS páginas oficiais divergentes (R$ 170 × R$ 275) — esta planilha não cobra essa faixa de propósito, então o custo real pode ser MAIOR. De 32 a 45 kg a GOL publica R$ 350/volume.","")
A29: =IF(SUM(COMITIVA!$J$6:$J$45)>0,"⚠ Há bagagem especial/diferenciada (case rígido). Lembre: na GOL, cliente Smiles NÃO tem gratuidade, tarifa com despacho grátis NÃO cobre a diferenciada, e a GOL não se responsabiliza por danos a bagagem diferenciada.","")
A30: =IF(PREMISSAS!$B$5="Azul","⚠ Azul: alto-falante, amplificador e caixa acústica são ARTIGO PERIGOSO — só até 95 cm somados e 1 por passageiro. Acima disso vai de Azul Cargo, não de bagagem. É isto que quebra o plano de levar backline na mala.","")
A31: =IF(PREMISSAS!$B$7<2,"⚠ Você está orçando bagagem em 1 trecho só. Despacho se paga POR TRECHO: ida e volta = 2.","")
A32: ="Lembrete: o PL 5041/2025 (12 kg de mão + 23 kg despachado grátis) NÃO é lei. Foi aprovado na Câmara em 28/10/2025 e está parado no Senado desde 05/11/2025. Blog que diz que já vale está errado — e quem orça por ele perde dinheiro."

Sheet TABELAS_OFICIAIS
A1: TABELAS OFICIAIS - snapshot 15/07/2026 (nao edite: dado de fonte)
A2: Preco de bagagem NAO e tabelado por lei: e contrato acessorio (Res. ANAC 400/2016, art. 13) e preco livre. Os valores abaixo sao SNAPSHOT de 15/07/2026 das paginas oficiais das cias e mudam sem aviso. Confira antes de fechar orcamento.
A4: A) DESPACHO NACIONAL - preco por peca, por trecho (R$)
A5: Chave (cia|antecedencia) | B5: Companhia | C5: Antecedencia | D5: 1a peca (R$) | E5: 2a peca (R$) | F5: 3a a 5a peca (R$) | G5: Fonte | H5: Snapshot
A6: GOL|48h ou mais | B6: GOL | C6: 48h ou mais | D6: 130 | E6: 155 | F6: 210 | G6: GOL - tabela publicada de bagagem nacional (_FATOS-VIAGEM.md, sec. 2) | H6: snapshot 15/07/2026
A7: GOL|menos de 48h | B7: GOL | C7: menos de 48h | D7: 165 | E7: 200 | F7: 280 | G7: GOL - tabela publicada de bagagem nacional (_FATOS-VIAGEM.md, sec. 2) | H7: snapshot 15/07/2026
A8: GOL|no aeroporto | B8: GOL | C8: no aeroporto | D8: 180 | E8: 200 | F8: 280 | G8: GOL - tabela publicada de bagagem nacional (_FATOS-VIAGEM.md, sec. 2) | H8: snapshot 15/07/2026
A9: Azul|48h ou mais | B9: Azul | C9: 48h ou mais | D9: 175 | E9: 200 | F9: 220 | G9: Azul - tabela publicada Brasil (_FATOS-VIAGEM.md, sec. 2) | H9: snapshot 15/07/2026
A10: Azul|menos de 48h | B10: Azul | C10: menos de 48h | D10: 200 | E10: 220 | F10: 280 | G10: Azul - tabela publicada Brasil (_FATOS-VIAGEM.md, sec. 2) | H10: snapshot 15/07/2026
A11: Azul|no aeroporto | B11: Azul | C11: no aeroporto | D11: nao publicado | E11: nao publicado | F11: nao publicado | G11: Azul nao publica preco de balcao/aeroporto. Azul - tabela publicada Brasil (_FATOS-VIAGEM.md, sec. 2) | H11: snapshot 15/07/2026
A12: LATAM|48h ou mais | B12: LATAM | C12: 48h ou mais | D12: nao publicado | E12: nao publicado | F12: nao publicado | G12: LATAM - preco DINAMICO, nao publicado (_FATOS-VIAGEM.md, sec. 2) | H12: snapshot 15/07/2026
A13: LATAM|menos de 48h | B13: LATAM | C13: menos de 48h | D13: nao publicado | E13: nao publicado | F13: nao publicado | G13: LATAM - preco DINAMICO, nao publicado (_FATOS-VIAGEM.md, sec. 2) | H13: snapshot 15/07/2026
A14: LATAM|no aeroporto | B14: LATAM | C14: no aeroporto | D14: nao publicado | E14: nao publicado | F14: nao publicado | G14: LATAM - preco DINAMICO, nao publicado (_FATOS-VIAGEM.md, sec. 2) | H14: snapshot 15/07/2026
A16: Azul: maximo de 5 pecas de 23 kg por passageiro/trecho. Fonte: _FATOS-VIAGEM.md sec. 2 (Azul Brasil publicado).
A17: NAO EXISTE NESTA PLANILHA a faixa de excesso 23->32 kg da GOL: duas paginas oficiais da GOL divergem (R$ 170 x R$ 275). Dado em conflito nao vira celula - vira alerta.
A19: B) EXCESSO DE PESO - 32 kg a 45 kg, por volume (R$)
A20: Companhia | B20: Excesso 32-45 kg (R$/volume) | C20: Observacao | D20: Fonte
A21: GOL | B21: 350 | C21: Excesso de 32 kg ate 45 kg por volume. Acima de 45 kg NAO transporta. | D21: GOL - tabela publicada de bagagem nacional (_FATOS-VIAGEM.md, sec. 2)
A22: Azul | B22: nao publicado | C22: Azul nao publica preco de excesso de peso. Recusa acima de 45 kg (BR) / 32 kg (Europa). | D22: Azul - tabela publicada Brasil (_FATOS-VIAGEM.md, sec. 2)
A23: LATAM | B23: nao publicado | C23: Preco dinamico, nao publicado. Nao transporta acima de 45 kg (32 kg em rotas especificas). | D23: LATAM - preco DINAMICO, nao publicado (_FATOS-VIAGEM.md, sec. 2)
A25: C) BAGAGEM ESPECIAL / DIFERENCIADA - case rigido obrigatorio (bumbo, contrabaixo, tuba, violoncelo) - por volume, por trecho (R$)
A26: Companhia | B26: Preco (R$/volume) | C26: Observacao | D26: Fonte
A27: GOL | B27: 195 | C27: 292 cm (A+B+C), ate 23 kg. Mesmo preco em +48h / -48h / aeroporto. Cliente Smiles NAO tem gratuidade; tarifa com despacho gratis NAO cobre a diferenciada; a GOL nao se responsabiliza por danos a bagagem diferenciada. | D27: GOL - tabela publicada de bagagem nacional (_FATOS-VIAGEM.md, sec. 2)
A28: Azul | B28: 250 | C28: Acima de 158 cm somados ja e ESPECIAL. Preco Brasil. | D28: Azul - tabela publicada Brasil (_FATOS-VIAGEM.md, sec. 2)
A29: LATAM | B29: nao publicado | C29: Limite 300 cm lineares. Preco nao publicado. Violao/guitarra com estojo = bagagem REGULAR (consome a franquia). | D29: LATAM - preco DINAMICO, nao publicado (_FATOS-VIAGEM.md, sec. 2)
A31: D) FRANQUIAS E LIMITES (dado de norma / contrato de cia)
A32: Tema | B32: Fato | C32: Fonte
A33: Bagagem de mao - franquia minima | B33: 10 kg. A norma NAO fixa dimensao: dimensao e quantidade sao do CONTRATO DE TRANSPORTE de cada cia. | C33: Res. ANAC 400/2016, art. 14
A34: MITO N.1 | B34: 55x35x25 cm NAO e 'padrao ANAC'. E contrato de cada companhia. | C34: Res. ANAC 400/2016, art. 14
A35: Bagagem despachada | B35: Configura CONTRATO ACESSORIO -> franquia gratis NAO e obrigatoria. | C35: Res. ANAC 400/2016, art. 13
A36: Bagagem fora das regras | B36: Pode ser RECUSADA ou submetida a contrato de transporte de CARGA. | C36: Res. ANAC 400/2016, art. 15
A37: Limite de indenizacao (domestico) | B37: 1.131 DES. | C37: Res. ANAC 400/2016, art. 17
A38: Peso por volume despachado | B38: 23 kg (GOL / Azul / LATAM). | C38: Cias - snapshot 15/07/2026
A39: Dimensao do volume despachado | B39: LATAM 158 cm lineares | GOL 80x50x28 | Azul 158 cm somados. | C39: Cias - snapshot 15/07/2026
A40: Recusa por peso | B40: Acima de 45 kg NAO transporta (GOL/Azul/LATAM no Brasil). 32 kg e limite internacional/Europa. | C40: Cias - snapshot 15/07/2026
A41: MITO N.3 | B41: '32 kg e o limite por saude do trabalhador' NAO vale no domestico brasileiro: as tres aceitam ate 45 kg por volume pagando excesso. | C41: Cias - snapshot 15/07/2026
A42: Item pessoal | B42: LATAM 45x35x20 10 kg | GOL 32x43x22 10 kg | Azul 45x35x20 SEM limite de peso. | C42: Cias - snapshot 15/07/2026
A43: Mala de cabine | B43: LATAM 55x35x25 12 kg (nao inclusa na Basic) | GOL 55x35x25 12 kg (desde 14/10/2025; antes 10 kg) | Azul 55x35x25 (115 cm) 10 kg. | C43: Cias - snapshot 15/07/2026
... A56: FRETAMENTO - troca de equipe | B56: Permitida substituicao de ATE 20% dos passageiros antes da partida. | C56: Res. ANTT 4.777/2015, art. 36
A58: TODO numero desta aba veio de _FATOS-VIAGEM.md (levantamento 15/07/2026). Onde a fonte oficial nao publica ou se contradiz, esta escrito 'nao publicado' de proposito - e as formulas das outras abas devolvem alerta em vez de um numero inventado.
