Workbook

Sheet PREMISSAS
A1: PREMISSAS - preencha SO as celulas AMARELAS. Todas as outras abas leem daqui.
A2: Regra da casa: uma celula, uma verdade. O numero de pessoas mora em B4 e SO em B4 - AEREO, RODOVIARIO, FRETAMENTO e RESUMO apontam para ela com referencia absoluta ($B$4). Mudou a comitiva? Muda B4 e a planilha inteira se recalcula. AMARELO = voce preenche | VERDE = dado de fonte oficial | CINZA = formula, nao digite por cima.
A4: Premissa | B4: Valor | C4: Unidade | D4: Origem do dado | E4: Por que isso importa
A5: Nº de pessoas na comitiva | B5: 8 | C5: pessoas | D5: PREMISSA DO ALUNO | E5: Multiplica quase tudo. Erre aqui e erre o orçamento inteiro.
A6: Nº de trechos (ida e volta = 2) | B6: 2 | C6: trechos | D6: PREMISSA DO ALUNO | E6: Bagagem se paga POR TRECHO, não por viagem. É o esquecimento clássico.
A7: Volumes despachados por pessoa (por trecho) | B7: 1 | C7: volumes | D7: PREMISSA DO ALUNO | E7: A 2ª e a 3ª peça custam mais caro que a 1ª.
A8: Peso de cada volume despachado | B8: 23 | C8: kg | D8: PREMISSA DO ALUNO — vem preenchida com 23 kg, que é o DADO OFICIAL da franquia por volume (GOL/Azul/LATAM, snapshot 15/07/2026) | E8: Acima de 32 kg entra excesso. Acima de 45 kg a cia RECUSA e vira carga (Res. ANAC 400/2016, art. 15).
A9: Companhia aérea | B9: GOL | C9: lista | D9: ESCOLHA (lista suspensa) | E9: LATAM não publica preço de despacho: é dinâmico. Escolha LATAM e veja a planilha avisar em vez de inventar.
A10: Antecedência da compra do despacho | B10: 48h ou mais | C10: lista | D10: ESCOLHA (lista suspensa) | E10: Comprar no aeroporto custa mais caro. Na GOL: R$ 130 antecipado x R$ 180 no balcão.
A11: Preço médio da passagem aérea (ida+volta, por pessoa) | B11: 1200 | C11: R$ | D11: PREMISSA DO ALUNO — coloque a SUA cotação | E11: Não existe tabela de passagem: preço é livre e muda por hora. O 1.200 aqui é só exemplo.
A12: Preço da passagem rodoviária (ida+volta, por pessoa) | B12: 380 | C12: R$ | D12: PREMISSA DO ALUNO — coloque a SUA cotação | E12: Idem. Exemplo — substitua.
A13: Custo do fretamento (veículo fechado, ida+volta) | B13: 9800 | C13: R$ | D13: PREMISSA DO ALUNO — coloque a SUA cotação | E13: Custo do CONTRATO, não por pessoa. Exemplo — substitua.
A14: Distância (só de ida) | B14: 1000 | C14: km | D14: PREMISSA DO ALUNO | E14: Serve para você conferir se as horas de estrada fazem sentido.
A15: Horas de viagem porta a porta — AÉREO | B15: 6 | C15: h | D15: PREMISSA DO ALUNO | E15: Inclui chegar 2 h antes, voo, esteira e traslado.
A16: Horas de viagem porta a porta — RODOVIÁRIO | B16: 16 | C16: h | D16: PREMISSA DO ALUNO | E16: É aqui que nasce a diária extra que ninguém orça.
A17: Diária da equipe | B17: 350 | C17: R$/pessoa/dia | D17: PREMISSA DO ALUNO | E17: O dia a mais na estrada é dia de cachê. Não é de graça.
A18: Diária de hotel | B18: 220 | C18: R$/pessoa/noite | D18: PREMISSA DO ALUNO | E18: A noite extra que a estrada gera.
A19: Custo de traslado por trecho | B19: 60 | C19: R$/pessoa/trecho | D19: PREMISSA DO ALUNO | E19: Van/carro casa-aeroporto e aeroporto-hotel.
A20: Nº de traslados — AÉREO | B20: 4 | C20: traslados/pessoa | D20: PREMISSA DO ALUNO | E20: Casa→aeroporto, aeroporto→hotel, e a volta.
A21: Nº de traslados — RODOVIÁRIO | B21: 2 | C21: traslados/pessoa | D21: PREMISSA DO ALUNO | E21: Rodoviária→hotel, ida e volta.
A22: Nº de traslados — FRETAMENTO | B22: 0 | C22: traslados/pessoa | D22: PREMISSA DO ALUNO | E22: O fretado costuma ser porta a porta. Se não for, ajuste.
... A24: Orçamento aprovado para transporte | B24: 20000 | C24: R$ | D24: PREMISSA DO ALUNO — é o que o cliente aprovou | E24: É contra isto que o RESUMO mede a folga.
A26: CALCULADO A PARTIR DAS PREMISSAS (não digite por cima)
A27: Chave de consulta da tabela oficial | B27: =$B$9&"|"&$B$10 | C27: texto | D27: FÓRMULA — monta a chave que o ÍNDICE+CORRESP usa em TABELAS_OFICIAIS
A28: Preço da 1ª peça despachada (resolvido) | B28: =IFERROR(INDEX(TABELAS_OFICIAIS!$D$6:$F$14,MATCH($B$27,TABELAS_OFICIAIS!$A$6:$A$14,0),1),"chave invalida") | C28: R$/peça/trecho | D28: TABELAS_OFICIAIS — dado oficial, snapshot 15/07/2026
A29: Preço da 2ª peça despachada (resolvido) | B29: =IFERROR(INDEX(TABELAS_OFICIAIS!$D$6:$F$14,MATCH($B$27,TABELAS_OFICIAIS!$A$6:$A$14,0),2),"chave invalida") | C29: R$/peça/trecho | D29: TABELAS_OFICIAIS — dado oficial, snapshot 15/07/2026
A30: Preço da 3ª a 5ª peça (resolvido) | B30: =IFERROR(INDEX(TABELAS_OFICIAIS!$D$6:$F$14,MATCH($B$27,TABELAS_OFICIAIS!$A$6:$A$14,0),3),"chave invalida") | C30: R$/peça/trecho | D30: TABELAS_OFICIAIS — dado oficial, snapshot 15/07/2026
A31: Preço do excesso 32–45 kg (resolvido) | B31: =IFERROR(INDEX(TABELAS_OFICIAIS!$B$21:$B$23,MATCH($B$9,TABELAS_OFICIAIS!$A$21:$A$23,0)),"chave invalida") | C31: R$/volume/trecho | D31: TABELAS_OFICIAIS — só a GOL publica (R$ 350)
A32: Dias extras de equipe que a estrada gera | B32: =ROUNDUP(($B$16-$B$15)*2/24,0) | C32: dias | D32: FÓRMULA — modelo: cada 24 h a mais de estrada (ida+volta) = 1 dia extra de equipe
A33: Noites extras de hotel que a estrada gera | B33: =$B$32 | C33: noites | D33: FÓRMULA — aponta para B32: uma célula, uma verdade
A34: Passageiros que podem ser substituídos no fretamento (20%) | B34: =ROUNDDOWN($B$5*0.2,0) | C34: pessoas | D34: Res. ANTT 4.777/2015, art. 36 — substituição de até 20% antes da partida

Sheet AEREO
A1: CUSTO AÉREO — comitiva
A2: Toda célula calculada é FÓRMULA. Nada aqui é digitado à mão. Os preços de bagagem vêm de TABELAS_OFICIAIS por ÍNDICE+CORRESP; o resto vem de PREMISSAS por referência absoluta ($B$5).
A4: Item de custo | B4: Qtde | C4: Unidade | D4: Valor unitário (R$) | E4: Total (R$) | F4: Fonte / observação
A5: Passagem aérea (ida+volta) | B5: =PREMISSAS!$B$5 | C5: pessoas | D5: =PREMISSAS!$B$11 | E5: =IFERROR(B5*D5,0) | F5: PREMISSA DO ALUNO. Não existe tabela de passagem — preço é livre.
A6: Despacho — 1ª peça | B6: =IF(PREMISSAS!$B$7>=1,PREMISSAS!$B$5*PREMISSAS!$B$6,0) | C6: peças × trechos | D6: =PREMISSAS!$B$28 | E6: =IF(B6=0,0,IF(ISNUMBER(D6),B6*D6,"n/d — cotar")) | F6: TABELAS_OFICIAIS (snapshot 15/07/2026). Res. ANAC 400/2016 art. 13: despacho é contrato acessório — não há franquia grátis obrigatória.
A7: Despacho — 2ª peça | B7: =IF(PREMISSAS!$B$7>=2,PREMISSAS!$B$5*PREMISSAS!$B$6,0) | C7: peças × trechos | D7: =PREMISSAS!$B$29 | E7: =IF(B7=0,0,IF(ISNUMBER(D7),B7*D7,"n/d — cotar")) | F7: TABELAS_OFICIAIS. A 2ª peça é mais cara que a 1ª.
A8: Despacho — 3ª a 5ª peça | B8: =MAX(0,MIN(PREMISSAS!$B$7,5)-2)*PREMISSAS!$B$5*PREMISSAS!$B$6 | C8: peças × trechos | D8: =PREMISSAS!$B$30 | E8: =IF(B8=0,0,IF(ISNUMBER(D8),B8*D8,"n/d — cotar")) | F8: TABELAS_OFICIAIS. Azul: máximo 5 peças de 23 kg por passageiro/trecho.
A9: Excesso de peso (32–45 kg) | B9: =IF(AND(PREMISSAS!$B$8>32,PREMISSAS!$B$8<=45),PREMISSAS!$B$7*PREMISSAS!$B$5*PREMISSAS!$B$6,0) | C9: volumes × trechos | D9: =PREMISSAS!$B$31 | E9: =IF(B9=0,0,IF(ISNUMBER(D9),B9*D9,"n/d — cotar")) | F9: TABELAS_OFICIAIS. Só a GOL publica (R$ 350). A faixa 23→32 kg da GOL NÃO está aqui: duas páginas oficiais divergem (R$ 170 × R$ 275).
A10: Traslado | B10: =PREMISSAS!$B$5*PREMISSAS!$B$20 | C10: pessoas × traslados | D10: =PREMISSAS!$B$19 | E10: =IFERROR(B10*D10,0) | F10: PREMISSA DO ALUNO.
A11: ↓ linhas livres — acrescente itens aqui
A18: TOTAL AÉREO | E18: =SUM(E5:E16) | F18: SOMA(E5:E16) — com folga de linhas de propósito.
A19: Custo aéreo por pessoa | E19: =IFERROR($E$18/PREMISSAS!$B$5,0)
A20: Bagagem despachada — subtotal | E20: =SUM(E6:E9) | F20: É este número que o fretamento faz desaparecer.
A22: ALERTAS AUTOMÁTICOS
A23: =IF(COUNTA(E5:E16)>COUNT(E5:E16),"⚠ Há item de bagagem SEM preço oficial publicado (a cia escolhida não publica). A SOMA está IGNORANDO esse item em silêncio — cote com a companhia antes de fechar.","ok — todos os itens têm preço oficial")
A24: =IF(AND(PREMISSAS!$B$8>23,PREMISSAS!$B$8<=32),"⚠ Faixa 23–32 kg: duas páginas oficiais da GOL divergem (R$ 170 × R$ 275). Dado em conflito não vira número — cote com a cia.","")
A25: =IF(PREMISSAS!$B$8>45,"⛔ RECUSADO: acima de 45 kg a cia não transporta como bagagem — vira contrato de CARGA (Res. ANAC 400/2016, art. 15).","")
A26: =IF(PREMISSAS!$B$9="LATAM","⚠ LATAM não publica preço de despacho (é dinâmico, varia por rota e antecedência). A planilha se recusa a inventar — cote.","")
A27: =IF(PREMISSAS!$B$6<2,"⚠ Você está pagando bagagem em 1 trecho só. Despacho se paga POR TRECHO: ida e volta = 2.","")

Sheet RODOVIARIO
A1: CUSTO RODOVIÁRIO — linha regular
A2: A lição desta aba está nas linhas 7 e 8. O ônibus parece barato porque quase todo orçamento para na passagem. A viagem longa gera dia de equipe e noite de hotel — e isso é dinheiro seu.
A4: Item de custo | B4: Qtde | C4: Unidade | D4: Valor unitário (R$) | E4: Total (R$) | F4: Fonte / observação
A5: Passagem rodoviária (ida+volta) | B5: =PREMISSAS!$B$5 | C5: pessoas | D5: =PREMISSAS!$B$12 | E5: =IFERROR(B5*D5,0) | F5: PREMISSA DO ALUNO.
A6: Excesso de bagagem (verba) | B6: 1 | C6: verba | D6: =PREMISSAS!$B$23 | E6: =IFERROR(B6*D6,0) | F6: SEM TABELA. Res. ANTT 6.033/2023: excesso virou serviço acessório — oferta facultativa e PREÇO LIVRE, e a empresa pode simplesmente RECUSAR. Franquia mínima: 30 kg / 300 dm³ / maior dimensão 1 m.
A7: Diária extra da equipe (gerada pela estrada) | B7: =PREMISSAS!$B$5*PREMISSAS!$B$32 | C7: pessoas × dias | D7: =PREMISSAS!$B$17 | E7: =IFERROR(B7*D7,0) | F7: O dia a mais na estrada é dia de cachê. Esta é a linha que some do orçamento de ônibus.
A8: Hotel extra (pernoite gerado pela estrada) | B8: =PREMISSAS!$B$5*PREMISSAS!$B$33 | C8: pessoas × noites | D8: =PREMISSAS!$B$18 | E8: =IFERROR(B8*D8,0) | F8: Idem. Se a estrada empurra a chegada para outro dia, alguém dorme em algum lugar.
A9: Traslado | B9: =PREMISSAS!$B$5*PREMISSAS!$B$21 | C9: pessoas × traslados | D9: =PREMISSAS!$B$19 | E9: =IFERROR(B9*D9,0) | F9: PREMISSA DO ALUNO.
A10: ↓ linhas livres — acrescente itens aqui
A18: TOTAL RODOVIÁRIO | E18: =SUM(E5:E16) | F18: SOMA(E5:E16) — com folga de linhas de propósito.
A19: Custo rodoviário por pessoa | E19: =IFERROR($E$18/PREMISSAS!$B$5,0)
A21: A ILUSÃO DO ÔNIBUS BARATO
A22: Total se você ESQUECER a diária e o hotel (o orçamento errado) | E22: =$E$18-$E$7-$E$8
A23: Quanto você teria escondido de si mesmo | E23: =$E$7+$E$8
A24: …em % do total rodoviário | E24: =IFERROR(($E$7+$E$8)/$E$18,0)
A25: =IF($E$18-$E$7-$E$8<AEREO!$E$18,"⚠ Sem a diária e o hotel, o ônibus PARECE mais barato que o avião. Com eles, olhe o RESUMO antes de decidir.","")

Sheet FRETAMENTO
A1: CUSTO FRETAMENTO — eventual, circuito fechado (Res. ANTT 4.777/2015)
A2: Fretamento EVENTUAL é a modalidade de equipe de evento (congressos, competições). Circuito fechado: o grupo sai da origem, percorre e volta à origem no mesmo veículo. Custo é do CONTRATO, não por pessoa — e não há venda de bilhete individual (é proibida).
A4: Item de custo | B4: Qtde | C4: Unidade | D4: Valor unitário (R$) | E4: Total (R$) | F4: Fonte / observação
A5: Fretamento eventual (veículo fechado, ida+volta) | B5: 1 | C5: contrato | D5: =PREMISSAS!$B$13 | E5: =IFERROR(B5*D5,0) | F5: PREMISSA DO ALUNO — coloque a sua cotação. Exija Termo de Autorização da ANTT (consulte o CNPJ no site), Licença de Viagem e relação de passageiros a bordo (art. 23).
A6: Bilhete individual | B6: 0 | C6: bilhetes | D6: 0 | E6: =IFERROR(B6*D6,0) | F6: Res. ANTT 4.777/2015: a venda de bilhete individual no fretamento é PROIBIDA. Fica zero de propósito.
A7: Diária extra da equipe (gerada pela estrada) | B7: =PREMISSAS!$B$5*PREMISSAS!$B$32 | C7: pessoas × dias | D7: =PREMISSAS!$B$17 | E7: =IFERROR(B7*D7,0) | F7: A estrada é a mesma do ônibus de linha: o dia extra continua existindo.
A8: Hotel extra (pernoite gerado pela estrada) | B8: =PREMISSAS!$B$5*PREMISSAS!$B$33 | C8: pessoas × noites | D8: =PREMISSAS!$B$18 | E8: =IFERROR(B8*D8,0) | F8: Idem.
A9: Traslado | B9: =PREMISSAS!$B$5*PREMISSAS!$B$22 | C9: pessoas × traslados | D9: =PREMISSAS!$B$19 | E9: =IFERROR(B9*D9,0) | F9: Premissa 0 por padrão: o fretado costuma ser porta a porta. Se não for, ajuste em PREMISSAS!B22.
A10: ↓ linhas livres — acrescente itens aqui
A18: TOTAL FRETAMENTO | E18: =SUM(E5:E16) | F18: SOMA(E5:E16) — com folga de linhas de propósito.
A19: Custo do fretamento por pessoa | E19: =IFERROR($E$18/PREMISSAS!$B$5,0)
A21: O QUE O FRETAMENTO DISPENSA (informativo — não entra no total)
A22: Bagagem despachada que você deixa de pagar (= subtotal de despacho do AÉREO) | E22: =AEREO!$E$20 | F22: No fretado o bagageiro é do veículo que você contratou — não há tabela de peça despachada por passageiro nem cobrança por trecho.
A23: Traslados que você deixa de pagar em relação ao aéreo | E23: =IFERROR((PREMISSAS!$B$20-PREMISSAS!$B$22)*PREMISSAS!$B$5*PREMISSAS!$B$19,0)
A24: Passageiros que você pode trocar antes da partida (até 20%) | E24: =PREMISSAS!$B$34 | F24: Res. ANTT 4.777/2015, art. 36 — margem real para troca de equipe.
A26: Antes de assinar: consulte a autorização da empresa por CNPJ no site da ANTT, confira o selo no ônibus, exija a Licença de Viagem e inspecione veículo e motorista. Documentos a bordo (art. 23): Licença de Viagem + relação de passageiros; também CRLV, CSV e apólice do seguro RC (art. 31 §3º). 'CITV' não existe — se alguém te mostrar um, é papel inventado.

Sheet RESUMO
A1: RESUMO — qual modal, e cabe no orçamento?
A2: Nada aqui é digitado. Tudo aponta para AEREO, RODOVIARIO, FRETAMENTO e PREMISSAS.
A4: Indicador | B4: AÉREO | C4: RODOVIÁRIO | D4: FRETAMENTO | E4: Observação
A5: Custo total (R$) | B5: =AEREO!$E$18 | C5: =RODOVIARIO!$E$18 | D5: =FRETAMENTO!$E$18 | E5: Cada um vem da SOMA da sua aba.
A6: Custo por pessoa (R$) | B6: =IFERROR(B5/PREMISSAS!$B$5,0) | C6: =IFERROR(C5/PREMISSAS!$B$5,0) | D6: =IFERROR(D5/PREMISSAS!$B$5,0)
A7: Horas porta a porta | B7: =PREMISSAS!$B$15 | C7: =PREMISSAS!$B$16 | D7: =PREMISSAS!$B$16 | E7: Estrada é estrada: linha e fretado gastam o mesmo tempo.
A8: Horas-equipe consumidas (ida+volta) | B8: =B7*PREMISSAS!$B$5*PREMISSAS!$B$6 | C8: =C7*PREMISSAS!$B$5*PREMISSAS!$B$6 | D8: =D7*PREMISSAS!$B$5*PREMISSAS!$B$6 | E8: Tempo de gente é custo, mesmo quando não vira linha.
A9: Cabe no orçamento? | B9: =IF(B5<=PREMISSAS!$B$24,"CABE","ESTOURA") | C9: =IF(C5<=PREMISSAS!$B$24,"CABE","ESTOURA") | D9: =IF(D5<=PREMISSAS!$B$24,"CABE","ESTOURA") | E9: Contra PREMISSAS!B24.
A10: Folga contra o orçamento (R$) | B10: =PREMISSAS!$B$24-B5 | C10: =PREMISSAS!$B$24-C5 | D10: =PREMISSAS!$B$24-D5 | E10: Negativo = estourou.
A11: Folga contra o orçamento (%) | B11: =IFERROR((PREMISSAS!$B$24-B5)/PREMISSAS!$B$24,0) | C11: =IFERROR((PREMISSAS!$B$24-C5)/PREMISSAS!$B$24,0) | D11: =IFERROR((PREMISSAS!$B$24-D5)/PREMISSAS!$B$24,0)
A13: COMPARAÇÃO
A14: Menor custo entre os três (R$) | B14: =MIN($B$5:$D$5)
A15: Diferença AÉREO − RODOVIÁRIO (R$) | B15: =$B$5-$C$5 | E15: Positivo = o aéreo custa isso a mais.
A16: Diferença AÉREO − RODOVIÁRIO (%) | B16: =IFERROR(($B$5-$C$5)/$C$5,0) | E16: Sobre o rodoviário.
A17: Diferença AÉREO − FRETAMENTO (R$) | B17: =$B$5-$D$5
A18: Diferença AÉREO − FRETAMENTO (%) | B18: =IFERROR(($B$5-$D$5)/$D$5,0) | E18: Sobre o fretamento.
A19: Diferença RODOVIÁRIO − FRETAMENTO (R$) | B19: =$C$5-$D$5
A20: Diferença RODOVIÁRIO − FRETAMENTO (%) | B20: =IFERROR(($C$5-$D$5)/$D$5,0)
A22: VEREDITO
A23: Avião x ônibus de linha | B23: =IF($B$5<$C$5,"AÉREO mais barato","RODOVIÁRIO mais barato")
A24: O mais barato dos três | B24: =IF($B$5=MIN($B$5:$D$5),"AÉREO é o mais barato",IF($C$5=MIN($B$5:$D$5),"RODOVIÁRIO é o mais barato","FRETAMENTO é o mais barato"))
A25: Alguma opção cabe no orçamento? | B25: =IF(MIN($B$5:$D$5)<=PREMISSAS!$B$24,"SIM — a mais barata cabe, com folga de "&TEXT(PREMISSAS!$B$24-MIN($B$5:$D$5),"R$ #,##0.00"),"NÃO — nem a mais barata cabe. Falta "&TEXT(MIN($B$5:$D$5)-PREMISSAS!$B$24,"R$ #,##0.00"))
A26: Ilusão do ônibus barato (o que a diária + hotel escondiam) | B26: ="Sem diária e hotel o ônibus daria "&TEXT(RODOVIARIO!$E$22,"R$ #,##0.00")&" — ou seja, você esconderia "&TEXT(RODOVIARIO!$E$23,"R$ #,##0.00")&" de si mesmo."
A27: Preço oficial de bagagem | B27: =AEREO!$A$23
A29: Custo não é a única variável: o aéreo devolve horas de equipe e reduz risco de atraso na passagem de som; o fretado carrega volume que o aéreo recusa (a Azul, por exemplo, trata amplificador e caixa acústica como artigo perigoso — só até 95 cm somados e 1 por passageiro; acima disso vira Azul Cargo). Decida com o número na mão, não no lugar dele.

Sheet TABELAS_OFICIAIS
A1: TABELAS OFICIAIS - snapshot 15/07/2026 (nao edite: dado de fonte)
A2: Preco de bagagem NAO e tabelado por lei: e contrato acessorio (Res. ANAC 400/2016, art. 13) e preco livre. Os valores abaixo sao SNAPSHOT de 15/07/2026 das paginas oficiais das cias e mudam sem aviso. Confira antes de fechar orcamento.
A4: A) DESPACHO NACIONAL - preco por peca, por trecho (R$)
A5: Chave (cia|antecedencia) | B5: Companhia | C5: Antecedencia | D5: 1a peca (R$) | E5: 2a peca (R$) | F5: 3a a 5a peca (R$) | G5: Fonte | H5: Snapshot
A6: GOL|48h ou mais | B6: GOL | C6: 48h ou mais | D6: 130 | E6: 155 | F6: 210 | G6: GOL - tabela publicada de bagagem nacional (_FATOS-VIAGEM.md, sec. 2) | H6: snapshot 15/07/2026
A7: GOL|menos de 48h | B7: GOL | C7: menos de 48h | D7: 165 | E7: 200 | F7: 280 | G7: GOL - tabela publicada de bagagem nacional (_FATOS-VIAGEM.md, sec. 2) | H7: snapshot 15/07/2026
A8: GOL|no aeroporto | B8: GOL | C8: no aeroporto | D8: 180 | E8: 200 | F8: 280 | G8: GOL - tabela publicada de bagagem nacional (_FATOS-VIAGEM.md, sec. 2) | H8: snapshot 15/07/2026
A9: Azul|48h ou mais | B9: Azul | C9: 48h ou mais | D9: 175 | E9: 200 | F9: 220 | G9: Azul - tabela publicada Brasil (_FATOS-VIAGEM.md, sec. 2) | H9: snapshot 15/07/2026
A10: Azul|menos de 48h | B10: Azul | C10: menos de 48h | D10: 200 | E10: 220 | F10: 280 | G10: Azul - tabela publicada Brasil (_FATOS-VIAGEM.md, sec. 2) | H10: snapshot 15/07/2026
A11: Azul|no aeroporto | B11: Azul | C11: no aeroporto | D11: nao publicado | E11: nao publicado | F11: nao publicado | G11: Azul nao publica preco de balcao/aeroporto. Azul - tabela publicada Brasil (_FATOS-VIAGEM.md, sec. 2) | H11: snapshot 15/07/2026
A12: LATAM|48h ou mais | B12: LATAM | C12: 48h ou mais | D12: nao publicado | E12: nao publicado | F12: nao publicado | G12: LATAM - preco DINAMICO, nao publicado (_FATOS-VIAGEM.md, sec. 2) | H12: snapshot 15/07/2026
A13: LATAM|menos de 48h | B13: LATAM | C13: menos de 48h | D13: nao publicado | E13: nao publicado | F13: nao publicado | G13: LATAM - preco DINAMICO, nao publicado (_FATOS-VIAGEM.md, sec. 2) | H13: snapshot 15/07/2026
A14: LATAM|no aeroporto | B14: LATAM | C14: no aeroporto | D14: nao publicado | E14: nao publicado | F14: nao publicado | G14: LATAM - preco DINAMICO, nao publicado (_FATOS-VIAGEM.md, sec. 2) | H14: snapshot 15/07/2026
A16: Azul: maximo de 5 pecas de 23 kg por passageiro/trecho. Fonte: _FATOS-VIAGEM.md sec. 2 (Azul Brasil publicado).
A17: NAO EXISTE NESTA PLANILHA a faixa de excesso 23->32 kg da GOL: duas paginas oficiais da GOL divergem (R$ 170 x R$ 275). Dado em conflito nao vira celula - vira alerta.
A19: B) EXCESSO DE PESO - 32 kg a 45 kg, por volume (R$)
A20: Companhia | B20: Excesso 32-45 kg (R$/volume) | C20: Observacao | D20: Fonte
A21: GOL | B21: 350 | C21: Excesso de 32 kg ate 45 kg por volume. Acima de 45 kg NAO transporta. | D21: GOL - tabela publicada de bagagem nacional (_FATOS-VIAGEM.md, sec. 2)
A22: Azul | B22: nao publicado | C22: Azul nao publica preco de excesso de peso. Recusa acima de 45 kg (BR) / 32 kg (Europa). | D22: Azul - tabela publicada Brasil (_FATOS-VIAGEM.md, sec. 2)
A23: LATAM | B23: nao publicado | C23: Preco dinamico, nao publicado. Nao transporta acima de 45 kg (32 kg em rotas especificas). | D23: LATAM - preco DINAMICO, nao publicado (_FATOS-VIAGEM.md, sec. 2)
A25: C) BAGAGEM ESPECIAL / DIFERENCIADA - case rigido obrigatorio (bumbo, contrabaixo, tuba, violoncelo) - por volume, por trecho (R$)
A26: Companhia | B26: Preco (R$/volume) | C26: Observacao | D26: Fonte
A27: GOL | B27: 195 | C27: 292 cm (A+B+C), ate 23 kg. Mesmo preco em +48h / -48h / aeroporto. Cliente Smiles NAO tem gratuidade; tarifa com despacho gratis NAO cobre a diferenciada; a GOL nao se responsabiliza por danos a bagagem diferenciada. | D27: GOL - tabela publicada de bagagem nacional (_FATOS-VIAGEM.md, sec. 2)
A28: Azul | B28: 250 | C28: Acima de 158 cm somados ja e ESPECIAL. Preco Brasil. | D28: Azul - tabela publicada Brasil (_FATOS-VIAGEM.md, sec. 2)
A29: LATAM | B29: nao publicado | C29: Limite 300 cm lineares. Preco nao publicado. Violao/guitarra com estojo = bagagem REGULAR (consome a franquia). | D29: LATAM - preco DINAMICO, nao publicado (_FATOS-VIAGEM.md, sec. 2)
A31: D) FRANQUIAS E LIMITES (dado de norma / contrato de cia)
A32: Tema | B32: Fato | C32: Fonte
A33: Bagagem de mao - franquia minima | B33: 10 kg. A norma NAO fixa dimensao: dimensao e quantidade sao do CONTRATO DE TRANSPORTE de cada cia. | C33: Res. ANAC 400/2016, art. 14
A34: MITO N.1 | B34: 55x35x25 cm NAO e 'padrao ANAC'. E contrato de cada companhia. | C34: Res. ANAC 400/2016, art. 14
A35: Bagagem despachada | B35: Configura CONTRATO ACESSORIO -> franquia gratis NAO e obrigatoria. | C35: Res. ANAC 400/2016, art. 13
A36: Bagagem fora das regras | B36: Pode ser RECUSADA ou submetida a contrato de transporte de CARGA. | C36: Res. ANAC 400/2016, art. 15
A37: Limite de indenizacao (domestico) | B37: 1.131 DES. | C37: Res. ANAC 400/2016, art. 17
A38: Peso por volume despachado | B38: 23 kg (GOL / Azul / LATAM). | C38: Cias - snapshot 15/07/2026
A39: Dimensao do volume despachado | B39: LATAM 158 cm lineares | GOL 80x50x28 | Azul 158 cm somados. | C39: Cias - snapshot 15/07/2026
A40: Recusa por peso | B40: Acima de 45 kg NAO transporta (GOL/Azul/LATAM no Brasil). 32 kg e limite internacional/Europa. | C40: Cias - snapshot 15/07/2026
A41: MITO N.3 | B41: '32 kg e o limite por saude do trabalhador' NAO vale no domestico brasileiro: as tres aceitam ate 45 kg por volume pagando excesso. | C41: Cias - snapshot 15/07/2026
A42: Item pessoal | B42: LATAM 45x35x20 10 kg | GOL 32x43x22 10 kg | Azul 45x35x20 SEM limite de peso. | C42: Cias - snapshot 15/07/2026
A43: Mala de cabine | B43: LATAM 55x35x25 12 kg (nao inclusa na Basic) | GOL 55x35x25 12 kg (desde 14/10/2025; antes 10 kg) | Azul 55x35x25 (115 cm) 10 kg. | C43: Cias - snapshot 15/07/2026
... A56: FRETAMENTO - troca de equipe | B56: Permitida substituicao de ATE 20% dos passageiros antes da partida. | C56: Res. ANTT 4.777/2015, art. 36
A58: TODO numero desta aba veio de _FATOS-VIAGEM.md (levantamento 15/07/2026). Onde a fonte oficial nao publica ou se contradiz, esta escrito 'nao publicado' de proposito - e as formulas das outras abas devolvem alerta em vez de um numero inventado.
